IE5600SPP/__init__.py
IE5600SPP/algo/__init__.py
IE5600SPP/algo/astar.py
IE5600SPP/grap/Graph.py
IE5600SPP/grap/__init__.py
spp_pkg/__init__.py
spp_pkg/algo/__init__.py
spp_pkg/algo/astar.py
spp_pkg/grap/Graph.py
spp_pkg/grap/__init__.py
IE5600SPP-0.1.1.dist-info/METADATA
IE5600SPP-0.1.1.dist-info/WHEEL
IE5600SPP-0.1.1.dist-info/top_level.txt
IE5600SPP-0.1.1.dist-info/RECORD
