Metadata-Version: 2.1
Name: IE5600SPP
Version: 0.1.1
Summary: A small Small demo of spp
Home-page: UNKNOWN
Author: yuanyl
Author-email: yiliang_yuan@u.nus.edu
License: UNKNOWN
Platform: UNKNOWN
Classifier: Programming Language :: Python :: 3
Classifier: License :: OSI Approved :: MIT License
Classifier: Operating System :: OS Independent
